zelock/__init__.py
zelock/zelock.py
zelock-1.1.5.dist-info/METADATA
zelock-1.1.5.dist-info/WHEEL
zelock-1.1.5.dist-info/top_level.txt
zelock-1.1.5.dist-info/RECORD
